{"Contact Email": "administracion@fincalosaljibes.com", "Address": "FINCA LOS ALJIBES , CARRETERA HORNA \u2013 P\u00c9TROLA, KM 11,5 , CHINCHILLA DE MONTE-ARAG\u00d3N (ALBACETE), 02520, SPAIN", "Site code": "10005245", "Technical contact": "Victor Talaya Zamora", "Technical email": "bodega@fincalosaljibes.com", "Commercial contact": "Manuel Lorenzo Morante", "Commercial email": "mlorenzo@fincalosaljibes.com", "Standard": "Food", "Account name": "SERVICIOS DE CONTRATAS R\u00daSTICAS E INDUSTRIALES, S.L."}