{"Contact Email": "pedidos@rodenasrivera.es", "Address": "POLIGONO SAN RAFAEL, PARCELA 28, C/ SUECIA, NAVE 2  C.P., HELLIN (ALBACETE), 02400, SPAIN", "Site code": "3866931", "Technical contact": "Roc\u00edo Flores Jim\u00e9nez Mar\u00edn", "Technical email": "rociof@rodenasrivera.com", "Commercial contact": "Juan Carlos S\u00e1nchez Carlos S\u00e1nchez", "Commercial email": "pedidos@rodenasrivera.es", "Standard": "Packaging Materials", "Account name": "Rod\u00e9nas y Rivera S.A. - Pol\u00edgono San Rafael"}