{"Contact Email": "marketing@picualia.com", "Address": "Ctra. Nacional IV , Madrid-C\u00e1diz km298,6 , Paraje Zaurdilla, Zaurdilla Bail\u00e9n (Ja\u00e9n), 23710, SPAIN", "Site code": "2022267", "Technical contact": "Emilio Artero V\u00e1zquez Artero V\u00e1zquez", "Technical email": "produccion@picualia.com", "Commercial contact": "Juan Antonio Parrilla Gonz\u00e1lez Antonio Parrilla Gonz\u00e1lez", "Commercial email": "marketing@picualia.com", "Standard": "Food", "Account name": "Agr\u00edcola de Bail\u00e9n Virgen de Zocueca S.C.A"}